{"states": {"RhodeIsland": {"tweets": [], "sentiment": null}, "Mississippi": {"tweets": [], "sentiment": null}, "NewYork": {"tweets": [], "sentiment": null}, "Oklahoma": {"tweets": [], "sentiment": null}, "Wyoming": {"tweets": [], "sentiment": null}, "Minnesota": {"tweets": [], "sentiment": null}, "Illinois": {"tweets": [{"sentiment": "0", "text": "Kasich campaigns at Portillo\u2019s in River North: CHICAGO \u2013 Republican Presidential candidate John Kasich stopped in\u2026 http://t.co/43uLIfXshO", "created_at": "2015-09-29 17:52:05", "userid": 55540658, "geotag": {"type": "Point", "coordinates": [41.88804564, -87.62626724]}, "id": 648918180316844032}, {"sentiment": "-0.27813", "text": "Presidential Candidate John Kasich- \"Please never ever ever go into\u2026 https://t.co/MDD8ZCinpJ", "created_at": "2015-09-29 19:47:07", "userid": 1344644353, "geotag": {"type": "Point", "coordinates": [41.8369, -87.6844]}, "id": 648947129763762176}, {"sentiment": "0", "text": "Republican Presidential Candidate John Kasich Makes Campaign Stop In Chicago: Ohio Governor John Kasich made a\u2026 http://t.co/4j3dX9Miev", "created_at": "2015-09-29 19:53:06", "userid": 55540658, "geotag": {"type": "Point", "coordinates": [41.88804564, -87.62626724]}, "id": 648948638299721728}, {"sentiment": "-0.437345", "text": "Kasich hits Chicago to raise money, sell himself to GOP voters: Ohio Gov. John Kasich came to Chicago on Tuesday to\u2026 http://t.co/IQQ10WpYOp", "created_at": "2015-09-29 19:53:07", "userid": 55540658, "geotag": {"type": "Point", "coordinates": [41.88804564, -87.62626724]}, "id": 648948640329805824}], "sentiment": {"percent_negitive_sentiment": 50.0, "overall_sentiment": -0.715475, "percent_positive_sentiment": 0.0}}, "Georgia": {"tweets": [], "sentiment": null}, "Arkansas": {"tweets": [], "sentiment": null}, "SouthCarolina": {"tweets": [], "sentiment": null}, "Ohio": {"tweets": [{"sentiment": "0", "text": "Kasich helped rewrite \"welfare reform\"in the 90's.Still not a MODERATE.  http://t.co/84FiWw0PJG", "created_at": "2015-09-21 15:52:55", "userid": 583117972, "geotag": {"type": "Point", "coordinates": [39.96396396, -82.96132053]}, "id": 645989089762803712}, {"sentiment": "-0.403798", "text": "Erickson seems to not be fond of Kasich.  http://t.co/TklKYyMWzJ", "created_at": "2015-09-23 00:49:09", "userid": 583117972, "geotag": {"type": "Point", "coordinates": [39.96396396, -82.96132053]}, "id": 646486423802126336}, {"sentiment": "0", "text": "Gov. Kasich appears on Late Night with Seth Meyers: Governor John Kasich tells Late Night host Seth Meyers he felt\u2026 http://t.co/ffCOcskpOQ", "created_at": "2015-09-23 09:59:02", "userid": 63964871, "geotag": {"type": "Point", "coordinates": [39.96378925, -82.99527267]}, "id": 646624809204322304}, {"sentiment": "0.201503", "text": "$5 Million Later, Has John Kasich Bought A New Hampshire Miracle Yet? -  http://t.co/wHhFIBgI3n", "created_at": "2015-09-27 06:32:50", "userid": 583117972, "geotag": {"type": "Point", "coordinates": [39.94594595, -82.96296919]}, "id": 648022466825179136}, {"sentiment": "0", "text": "DEAR JOHN KASICH... #ppswo #psquared #standwithpp #istandwithpp #PinkOut @ppact #reprorights\u2026 https://t.co/7UZyA4RGEC", "created_at": "2015-09-29 17:25:49", "userid": 542168047, "geotag": {"type": "Point", "coordinates": [39.1237717, -84.5080032]}, "id": 648911572094554112}, {"sentiment": "-0.778981", "text": "Kasich: Ohio's renewable energy freeze is 'unacceptable': Gov. John Kasich says a legislative committee's\u2026 http://t.co/WzK5sCrHGD", "created_at": "2015-09-30 15:29:05", "userid": 63964871, "geotag": {"type": "Point", "coordinates": [39.96378925, -82.99527267]}, "id": 649244583205859328}], "sentiment": {"percent_negitive_sentiment": 33.333333333333336, "overall_sentiment": -0.981276, "percent_positive_sentiment": 16.666666666666668}}, "Indiana": {"tweets": [{"sentiment": "0", "text": "DEAR JOHN KASICH... #ppswo #psquared #standwithpp #istandwithpp #PinkOut @ppact #reprorights\u2026 https://t.co/7UZyA4RGEC", "created_at": "2015-09-29 17:25:49", "userid": 542168047, "geotag": {"type": "Point", "coordinates": [39.1237717, -84.5080032]}, "id": 648911572094554112}], "sentiment": {"percent_negitive_sentiment": 0.0, "overall_sentiment": 0.0, "percent_positive_sentiment": 0.0}}, "Maryland": {"tweets": [], "sentiment": null}, "Louisiana": {"tweets": [], "sentiment": null}, "Idaho": {"tweets": [], "sentiment": null}, "NewHampshire": {"tweets": [], "sentiment": null}, "Arizona": {"tweets": [], "sentiment": null}, "Iowa": {"tweets": [], "sentiment": null}, "Michigan": {"tweets": [], "sentiment": null}, "Kansas": {"tweets": [], "sentiment": null}, "Utah": {"tweets": [], "sentiment": null}, "Virginia": {"tweets": [{"sentiment": "0", "text": "Ohio Politics Now: What Walker leaving the presidential race means for Kasich\u2026 http://t.co/X0FB6mDSgI #Politics #Pol http://t.co/WJAeWrTAXu", "created_at": "2015-09-22 13:28:42", "userid": 28918980, "geotag": {"type": "Point", "coordinates": [36.07265511, -79.78996754]}, "id": 646315185582403585}], "sentiment": {"percent_negitive_sentiment": 0.0, "overall_sentiment": 0.0, "percent_positive_sentiment": 0.0}}, "Oregon": {"tweets": [], "sentiment": null}, "Connecticut": {"tweets": [], "sentiment": null}, "Montana": {"tweets": [], "sentiment": null}, "California": {"tweets": [], "sentiment": null}, "Massachusetts": {"tweets": [], "sentiment": null}, "NewMexico": {"tweets": [], "sentiment": null}, "Vermont": {"tweets": [], "sentiment": null}, "Delaware": {"tweets": [], "sentiment": null}, "Pennsylvania": {"tweets": [], "sentiment": null}, "NorthCarolina": {"tweets": [{"sentiment": "0", "text": "Ohio Politics Now: What Walker leaving the presidential race means for Kasich\u2026 http://t.co/X0FB6mDSgI #Politics #Pol http://t.co/WJAeWrTAXu", "created_at": "2015-09-22 13:28:42", "userid": 28918980, "geotag": {"type": "Point", "coordinates": [36.07265511, -79.78996754]}, "id": 646315185582403585}], "sentiment": {"percent_negitive_sentiment": 0.0, "overall_sentiment": 0.0, "percent_positive_sentiment": 0.0}}, "Florida": {"tweets": [{"sentiment": "0.713147", "text": "Very true. RT @Political_Bill RT @ChicoDelainky I have my eye on John Kasich, I think he would be a (cont) http://t.co/uv4GCM2ohs", "created_at": "2015-09-30 20:43:04", "userid": 55425945, "geotag": {"type": "Point", "coordinates": [28.59459459, -81.48890328]}, "id": 649323599086645248}, {"sentiment": "0.72097", "text": "RT @bmwash374: Very true. RT @Political_Bill RT @ChicoDelainky I have my eye on John Kasich, I think he would be a (cont) http://t.co/uv4GC\u2026", "created_at": "2015-09-30 20:44:12", "userid": 16790797, "geotag": null, "id": 649323886098685953}], "sentiment": {"percent_negitive_sentiment": 0.0, "overall_sentiment": 1.434117, "percent_positive_sentiment": 100.0}}, "Alaska": {"tweets": [], "sentiment": null}, "Kentucky": {"tweets": [{"sentiment": "0", "text": "DEAR JOHN KASICH... #ppswo #psquared #standwithpp #istandwithpp #PinkOut @ppact #reprorights\u2026 https://t.co/7UZyA4RGEC", "created_at": "2015-09-29 17:25:49", "userid": 542168047, "geotag": {"type": "Point", "coordinates": [39.1237717, -84.5080032]}, "id": 648911572094554112}], "sentiment": {"percent_negitive_sentiment": 0.0, "overall_sentiment": 0.0, "percent_positive_sentiment": 0.0}}, "Hawaii": {"tweets": [], "sentiment": null}, "Nebraska": {"tweets": [], "sentiment": null}, "WestVirginia": {"tweets": [], "sentiment": null}, "Missouri": {"tweets": [], "sentiment": null}, "Wisconsin": {"tweets": [], "sentiment": null}, "Alabama": {"tweets": [], "sentiment": null}, "Colorado": {"tweets": [], "sentiment": null}, "DistrictOfColumbia": {"tweets": [], "sentiment": null}, "NewJersey": {"tweets": [], "sentiment": null}, "Washington": {"tweets": [{"sentiment": "-0.469729", "text": "RT @SeattleCP: A buffoon leads GOP pack, and a quality candidate languishes: OK, OK. I\u2019m in Ohio, watching Gov. John Kasich become\u2026 http://\u2026", "created_at": "2015-09-28 07:16:30", "userid": 151988871, "geotag": null, "id": 648395842563403776}], "sentiment": {"percent_negitive_sentiment": 100.0, "overall_sentiment": -0.469729, "percent_positive_sentiment": 0.0}}, "Maine": {"tweets": [], "sentiment": null}, "Tennessee": {"tweets": [], "sentiment": null}, "NorthDakota": {"tweets": [], "sentiment": null}, "Texas": {"tweets": [], "sentiment": null}, "Nevada": {"tweets": [], "sentiment": null}, "SouthDakota": {"tweets": [], "sentiment": null}}, "candidate": "John Kasich"}